tests/__init__.py
tests/test_sample.py
tests/test_util.py
wrapplotly/_20210516_wordcloud.py
wrapplotly/__init__.py
wrapplotly/_example_plot_wordcloud.py
wrapplotly/_wordcloud_annotate.py
wrapplotly/graphics.py
wrapplotly/plot_wordcloud.py
wrapplotly/util.py
wrapplotly-0.0.3.dist-info/LICENSE
wrapplotly-0.0.3.dist-info/METADATA
wrapplotly-0.0.3.dist-info/WHEEL
wrapplotly-0.0.3.dist-info/top_level.txt
wrapplotly-0.0.3.dist-info/RECORD
