Metadata-Version: 2.1
Name: wrapplotly
Version: 0.0.3
Summary: A plotly wrapper allowing subplots, single plots and word clouds
Home-page: https://github.com/jill-augustine/wrapplotly
Author: Jillian Augustine
Author-email: jaugur.ds@gmail.com
License: UNKNOWN
Platform: UNKNOWN
Classifier: Programming Language :: Python :: 3
Classifier: License :: OSI Approved :: MIT License
Classifier: Operating System :: OS Independent
Requires-Python: >=3.7
